LICENSE
README.md
pyproject.toml
setup.py
arris_dcx960/__init__.py
arris_dcx960/__version__.py
arris_dcx960/arrisdcx960.py
arris_dcx960/arrisdcx960box.py
arris_dcx960/const.py
arris_dcx960/exceptions.py
arris_dcx960/helpers.py
arris_dcx960/models.py
arris_dcx960.egg-info/PKG-INFO
arris_dcx960.egg-info/SOURCES.txt
arris_dcx960.egg-info/dependency_links.txt
arris_dcx960.egg-info/not-zip-safe
arris_dcx960.egg-info/requires.txt
arris_dcx960.egg-info/top_level.txt