Metadata-Version: 2.1
Name: arris-dcx960
Version: 0.1.1
Summary: Python client for Arris DCX960 settop boxes
Home-page: https://github.com/sholofly/arrisdcx960-python
Author: Rudolf Offereins
Author-email: r.offereins@gmail.com
License: MIT license
Keywords: Arris DCX960,API,Aettop box
Platform: UNKNOWN
Classifier: Development Status :: 3 - Alpha
Classifier: Programming Language :: Python :: 3
Classifier: License :: OSI Approved :: MIT License
Classifier: Operating System :: OS Independent
Classifier: Natural Language :: English
Classifier: Intended Audience :: Developers
Classifier: Programming Language :: Python :: 3.6
Classifier: Programming Language :: Python :: 3.7
Classifier: Programming Language :: Python :: 3
Classifier: Topic :: Software Development :: Libraries :: Python Modules
Requires-Python: >=3.6
License-File: LICENSE
